{
  "tobaccoProducts": false,
  "products": [
    {
      "productId": "5283196-EA-000",
      "brand": "Aveeno",
      "name": "Fresh Greens Blend Refresh & Thicken Conditioner",
      "displayName": "354ml",
      "availability": [
        "IN_STORE",
        "ONLINE"
      ],
      "saleType": "UNITS",
      "restrictedFlag": false,
      "liquorFlag": false,
      "tobaccoFlag": false,
      "originRegulated": false,
      "singlePrice": {
        "price": 2019,
        "comparativePrice": {
          "pricePerUnit": 570,
          "unitQuantity": 100,
          "unitQuantityUom": "ml",
          "measureDescription": "100ml"
        }
      },
      "promotions": [
        {
          "promoId": "0403786253",
          "rewardValue": 999,
          "decal": "4000",
          "sapType": "BASE",
          "rewardType": "NEW_PRICE",
          "threshold": 1,
          "multiProducts": true,
          "cardDependencyFlag": true,
          "bestPromotion": true,
          "comparativePrice": {
            "pricePerUnit": 282,
            "unitQuantity": 100,
            "unitQuantityUom": "ml",
            "measureDescription": "100ml"
          }
        }
      ],
      "facets": [
        {
          "itemCode": "00020012",
          "itemDescription": "Non-GMO"
        }
      ],
      "categoryTrees": [
        {
          "level0": "Health & Body",
          "level1": "Hair Care",
          "level2": "Conditioner"
        }
      ],
      "cateredFlag": false
    },
    {
      "productId": "5283208-EA-000",
      "brand": "Aveeno",
      "name": "Oat Milk Blend Daily Moisture Conditioner",
      "displayName": "354ml",
      "availability": [
        "IN_STORE",
        "ONLINE"
      ],
      "saleType": "UNITS",
      "restrictedFlag": false,
      "liquorFlag": false,
      "tobaccoFlag": false,
      "originRegulated": false,
      "singlePrice": {
        "price": 2019,
        "comparativePrice": {
          "pricePerUnit": 570,
          "unitQuantity": 100,
          "unitQuantityUom": "ml",
          "measureDescription": "100ml"
        }
      },
      "promotions": [
        {
          "promoId": "0403786253",
          "rewardValue": 999,
          "decal": "4000",
          "sapType": "BASE",
          "rewardType": "NEW_PRICE",
          "threshold": 1,
          "multiProducts": true,
          "cardDependencyFlag": true,
          "bestPromotion": true,
          "comparativePrice": {
            "pricePerUnit": 282,
            "unitQuantity": 100,
            "unitQuantityUom": "ml",
            "measureDescription": "100ml"
          }
        }
      ],
      "facets": [
        {
          "itemCode": "00020012",
          "itemDescription": "Non-GMO"
        }
      ],
      "categoryTrees": [
        {
          "level0": "Health & Body",
          "level1": "Hair Care",
          "level2": "Conditioner"
        }
      ],
      "cateredFlag": false
    },
    {
      "productId": "5283209-EA-000",
      "brand": "Aveeno",
      "name": "Apple Cider Vinegar Blend Clarify & Shine Conditioner",
      "displayName": "354ml",
      "availability": [
        "IN_STORE",
        "ONLINE"
      ],
      "saleType": "UNITS",
      "restrictedFlag": false,
      "liquorFlag": false,
      "tobaccoFlag": false,
      "originRegulated": false,
      "singlePrice": {
        "price": 2019,
        "comparativePrice": {
          "pricePerUnit": 570,
          "unitQuantity": 100,
          "unitQuantityUom": "ml",
          "measureDescription": "100ml"
        }
      },
      "promotions": [
        {
          "promoId": "0403786253",
          "rewardValue": 999,
          "decal": "4000",
          "sapType": "BASE",
          "rewardType": "NEW_PRICE",
          "threshold": 1,
          "multiProducts": true,
          "cardDependencyFlag": true,
          "bestPromotion": true,
          "comparativePrice": {
            "pricePerUnit": 282,
            "unitQuantity": 100,
            "unitQuantityUom": "ml",
            "measureDescription": "100ml"
          }
        }
      ],
      "facets": [
        {
          "itemCode": "00020012",
          "itemDescription": "Non-GMO"
        }
      ],
      "categoryTrees": [
        {
          "level0": "Health & Body",
          "level1": "Hair Care",
          "level2": "Conditioner"
        }
      ],
      "cateredFlag": false
    },
    {
      "productId": "5283204-EA-000",
      "brand": "Aveeno",
      "name": "Rose Water & Chamomile Blend Soothe & Soften Conditioner",
      "displayName": "354ml",
      "availability": [
        "IN_STORE",
        "ONLINE"
      ],
      "saleType": "UNITS",
      "restrictedFlag": false,
      "liquorFlag": false,
      "tobaccoFlag": false,
      "originRegulated": false,
      "singlePrice": {
        "price": 2019,
        "comparativePrice": {
          "pricePerUnit": 570,
          "unitQuantity": 100,
          "unitQuantityUom": "ml",
          "measureDescription": "100ml"
        }
      },
      "promotions": [
        {
          "promoId": "0403786253",
          "rewardValue": 999,
          "decal": "4000",
          "sapType": "BASE",
          "rewardType": "NEW_PRICE",
          "threshold": 1,
          "multiProducts": true,
          "cardDependencyFlag": true,
          "bestPromotion": true,
          "comparativePrice": {
            "pricePerUnit": 282,
            "unitQuantity": 100,
            "unitQuantityUom": "ml",
            "measureDescription": "100ml"
          }
        }
      ],
      "facets": [
        {
          "itemCode": "00020012",
          "itemDescription": "Non-GMO"
        }
      ],
      "categoryTrees": [
        {
          "level0": "Health & Body",
          "level1": "Hair Care",
          "level2": "Conditioner"
        }
      ],
      "cateredFlag": false
    }
  ],
  "algoliaSearchResult": {
    "facets": {
      "brand": {
        "Aveeno": 4
      },
      "tobacco": {
        "false": 4
      },
      "category1SI": {
        "Hair Care": 4
      },
      "onPromotion": {
        "0637c08c-ac36-4940-8582-38e44a4812fa": 4,
        "12c83069-9220-466b-9145-6ac5706d841c": 4,
        "2de22d8e-54d4-4575-be10-0d783324ec75": 4,
        "341f876f-9a83-4882-aa79-5e5c9dc8fb2e": 4,
        "3ee7214b-6df4-4fdb-9dd6-3b2fc252ba6b": 4,
        "401accb9-6430-45a1-888d-29337ab34f12": 4,
        "421d563e-ce40-4d5c-a79c-4afb521fc5b0": 4,
        "4f76214d-40a5-4c71-a94f-81d45f3f0a59": 4,
        "5080816d-825d-4a6e-9835-a93d986b1ee0": 4,
        "50a98f3b-ffbd-4229-84bc-bfd3c956119f": 4,
        "81f807e9-1879-484c-b27e-ded56245c6a4": 4,
        "8d098344-5474-4626-ae1c-90ed0f57306f": 4,
        "8e5b742c-0957-4b97-b9e2-290d75c02046": 4,
        "95d161ea-9a31-4fca-acbe-96f271d627df": 4,
        "afbe3446-1f57-4dca-9a58-0c7d5a4a6020": 4,
        "b007db90-0a16-47d8-9a89-407be8496d9a": 4,
        "b7fe0c9e-24e9-46f2-a59a-95dce1725b06": 4,
        "bae1da58-ac6b-4ef2-816d-4932691218d1": 4,
        "bfe3a4ae-2f6d-46ed-ba60-28451a4807bf": 4,
        "ca27a97f-03d4-4969-9400-e3af61c99816": 4,
        "d0914aa0-ab30-4354-a223-6ba9ef6069c1": 4,
        "f7f6ce3e-c7f6-459a-8466-e29d868257d1": 4,
        "fc91d59f-6ab5-4447-8737-125e09e8e50e": 4,
        "04ba529d-3dee-4f86-adb6-62b0111114d7": 3,
        "30a90cf9-3547-46d1-b8b1-cc9ff4af5f88": 3,
        "5b8f8e3b-e1a0-4a11-b16b-9cfe782c124e": 3,
        "6ea5a1cf-56b8-44eb-856c-fd916560e92e": 3,
        "756356f9-9985-40c9-a368-bf1ea8072b0e": 3,
        "80bebcaf-d5a3-4ca6-a999-beab902aef55": 3,
        "84c3115a-fe09-4bc3-b373-f43cc9e9627c": 3,
        "9829c627-42c8-4ad7-b550-f9dba9fcd44a": 3,
        "b3158cd8-72b9-40e5-8c4e-abd43c1be305": 3,
        "c1aaac72-38c0-4cc0-ad05-f241047d88c5": 3,
        "c6abac35-b75f-4a02-9b43-7ad5a7c7aa37": 3,
        "d83b5f5e-db6e-4696-823e-5940493ef41c": 3,
        "e197b67e-2cf9-4bae-bae5-5b8ffdccfa87": 3,
        "ff528de5-233a-4cf6-a3a9-bc140565367e": 3,
        "10de9574-cf98-4bc8-973d-3d3e36cb0c4d": 2,
        "5c3070dd-312f-4755-a92c-7607b2a694e4": 2,
        "a7c2a0cc-d39d-4b26-93ba-09adaa3a8bf6": 2,
        "91b26327-b240-4778-a3d8-190dfc8c16f3": 1,
        "a0d86b5f-fdf4-44d1-b7a2-f418bdb37f4e": 1,
        "e3a57a0b-156f-4994-a06a-921df65c20cc": 1
      },
      "productFacets": {
        "Non-GMO": 4
      }
    }
  },
  "algoliaFacetQueriesResults": [],
  "totalHits": 4,
  "page": 0,
  "totalPages": 1,
  "hitsPerPage": 50
}